[
  {
    "marca": "Mitsubishi",
    "numerodechassi": "Mitsubishi1",
    "imagemmarca": "https://www.carlogos.org/logo/Mitsubishi-logo-2000x2500.png",
    "modelo": "Evolution VIII",
    "preco": 52500,
    "tipodechassi": "Sedan",
    "estado": "Usado",
    "anofabrico": "2006",
    "numerokm": 51901,
    "potencia": 256,
    "capacidade": 5204,
    "combustivel": "Gasoline",
    "corexterior": "Silver Gray",
    "tranmissao": "Manual",
    "portas": 5,
    "imagens": [
      "https://cdn.easysite.pt/pub/6532/804978/EDN_NCAUTO_20319525-0.jpg",
      "https://cdn.easysite.pt/pub/6532/804978/EDN_NCAUTO_20319519-0.jpg",
      "https://cdn.easysite.pt/pub/6532/804978/EDN_NCAUTO_20319523-0.jpg"
    ],
    "sensores": "n/a",
    "seguranca": [
      "ABS",
      "Airbag do passageiro",
      "Controlo de estabilidade (ESP)",
      "Airbag do condutor"
    ],
    "tipofarois": "Led"
  },
  {
    "marca": "Bmw",
    "numerodechassi": "Bmw1",
    "imagemmarca": "https://www.autokuatrus.pt/images/sampledata/cars_logo/bmw.png",
    "modelo": "116 EXECUTIVE",
    "preco": 17990,
    "tipodechassi": "Sedan",
    "estado": "Used",
    "anofabrico": "2016",
    "numerokm": 144000,
    "potencia": 116,
    "capacidade": 1496,
    "combustivel": "Diesel",
    "corexterior": "Black",
    "tranmissao": "Manual",
    "portas": 5,
    "imagens": [
      "https://www.autokuatrus.pt/media/com_expautospro/images/big/1906_4.jpg",
      "https://www.autokuatrus.pt/media/com_expautospro/images/big/1906_6.jpg",
      "https://www.autokuatrus.pt/media/com_expautospro/images/big/1906_2.jpg"
    ],
    "sensores": "n/a",
    "seguranca": [
      "ABS",
      "Airbag do passageiro",
      "Controlo de estabilidade (ESP)",
      "Airbag do condutor"
    ],
    "tipofarois": "No Info"
  },
  {
    "marca": "Ford",
    "numerodechassi": "Ford1",
    "imagemmarca": "https://www.autokuatrus.pt/images/sampledata/cars_logo/ford.png",
    "modelo": "MK2 2.5 Ultimate",
    "preco": 90000,
    "tipodechassi": "Coupe",
    "estado": "Used",
    "anofabrico": "1992",
    "numerokm": 19815,
    "potencia": 350,
    "capacidade": 5204,
    "combustivel": "Gasoline",
    "corexterior": "White",
    "tranmissao": "Manual",
    "portas": 2,
    "imagens": [
      "https://cdn.easysite.pt/pub/6532/976183/EDN_NCAUTO_21304482-0.jpg",
      "https://cdn.easysite.pt/pub/6532/976183/EDN_NCAUTO_21304476-0.jpg",
      "https://cdn.easysite.pt/pub/6532/976183/EDN_NCAUTO_21304474-0.jpg"
    ],
    "sensores": "n/a",
    "seguranca": [
      "ABS",
      "Airbag do passageiro",
      "Controlo de estabilidade (ESP)",
      "Airbag do condutor"
    ],
    "tipofarois": "No Info"
  },
  {
    "marca": "Renault",
    "numerodechassi": "Renault1",
    "imagemmarca": "https://www.autokuatrus.pt/images/sampledata/cars_logo/renault.png",
    "modelo": "Clio 1.8 16v",
    "preco": 14000,
    "tipodechassi": "Citadino",
    "estado": "Used",
    "anofabrico": "1995",
    "numerokm": 131107,
    "potencia": 138,
    "capacidade": 1764,
    "combustivel": "Gasoline",
    "corexterior": "Gray",
    "tranmissao": "Manual",
    "portas": 3,
    "imagens": [
      "https://cdn.easysite.pt/pub/6532/957112/EDN_NCAUTO_18389994-0.jpg",
      "https://cdn.easysite.pt/pub/6532/957112/EDN_NCAUTO_18389981-0.jpg",
      "https://cdn.easysite.pt/pub/6532/957112/EDN_NCAUTO_18389987-0.jpg"
    ],
    "sensores": "n/a",
    "seguranca": [
      "ABS",
      "Airbag do passageiro",
      "Controlo de estabilidade (ESP)",
      "Airbag do condutor"
    ],
    "tipofarois": "No Info"
  },
  {
    "marca": "Citroen",
    "numerodechassi": "Citroen1",
    "imagemmarca": "https://www.autokuatrus.pt/images/sampledata/cars_logo/citroen.png",
    "modelo": "C4 Cactus 1.6 BlueHDi Shine 100cv 1560CC",
    "preco": 29990,
    "tipodechassi": "Suv",
    "estado": "Used",
    "anofabrico": "2018",
    "numerokm": 105379,
    "potencia": 150,
    "capacidade": 1999,
    "combustivel": "Diesel",
    "corexterior": "Black",
    "tranmissao": "Manual",
    "portas": 5,
    "imagens": [
      "https://www.autokuatrus.pt/media/com_expautospro/images/big/1698_1.jpg",
      "https://www.autokuatrus.pt/media/com_expautospro/images/big/1698_0.jpg",
      "https://www.autokuatrus.pt/media/com_expautospro/images/big/1698_2.jpg"
    ],
    "sensores": "Yes",
    "seguranca": [
      "ABS",
      "Airbag do passageiro",
      "Controlo de estabilidade (ESP)",
      "Airbag do condutor"
    ],
    "tipofarois": "bi-led"
  },
  {
    "marca": "Peugeot",
    "numerodechassi": "Peugeot1",
    "imagemmarca": "https://www.autokuatrus.pt/images/sampledata/cars_logo/peugeot.png",
    "modelo": "5008 1.6 BlueHDi Allure 120cv 1560CC",
    "preco": 18990,
    "tipodechassi": "MonoVolume",
    "estado": "Used",
    "anofabrico": "2016",
    "numerokm": 93776,
    "potencia": 120,
    "capacidade": 1560,
    "combustivel": "Diesel",
    "corexterior": "Gray",
    "tranmissao": "Manual",
    "portas": 5,
    "imagens": [
      "https://www.autokuatrus.pt/media/com_expautospro/images/big/1756_0.jpg",
      "https://www.autokuatrus.pt/media/com_expautospro/images/big/1756_2.jpg",
      "https://www.autokuatrus.pt/media/com_expautospro/images/big/1756_1.jpg"
    ],
    "sensores": "Yes",
    "seguranca": [
      "ABS",
      "Airbag do passageiro",
      "Controlo de estabilidade (ESP)",
      "Airbag do condutor"
    ],
    "tipofarois": "bi-led"
  },
  {
    "marca": "Mercedes",
    "numerodechassi": "Mercedes1",
    "imagemmarca": "https://www.autokuatrus.pt/images/sampledata/cars_logo/MercedesBenzLogo.png",
    "modelo": "Benz G 300 w463",
    "preco": 36500,
    "tipodechassi": "Suv",
    "estado": "Used",
    "anofabrico": "1992",
    "numerokm": 367474,
    "potencia": 112,
    "capacidade": 5204,
    "combustivel": "Diesel",
    "corexterior": "Dark Green",
    "tranmissao": "Manual",
    "portas": 5,
    "imagens": [
      "https://cdn.easysite.pt/pub/6532/861118/EDN_NCAUTO_13683709-0.jpg",
      "https://cdn.easysite.pt/pub/6532/861118/EDN_NCAUTO_13683708-0.jpg",
      "https://cdn.easysite.pt/pub/6532/861118/EDN_NCAUTO_13683711-0.jpg"
    ],
    "sensores": "n/a",
    "seguranca": [
      "ABS",
      "Airbag do passageiro",
      "Controlo de estabilidade (ESP)",
      "Airbag do condutor"
    ],
    "tipofarois": "Xenon & Led"
  },
  {
    "marca": "Opel",
    "numerodechassi": "Opel1",
    "imagemmarca": "https://www.autokuatrus.pt/images/sampledata/cars_logo/opel.png",
    "modelo": "Corsa ECO FLEX 90cv 1000CC",
    "preco": 10900,
    "tipodechassi": "Citadino",
    "estado": "Used",
    "anofabrico": "2015",
    "numerokm": 128000,
    "potencia": 90,
    "capacidade": 1000,
    "combustivel": "Gsoline",
    "corexterior": "White",
    "tranmissao": "Manual",
    "portas": 5,
    "imagens": [
      "https://www.autokuatrus.pt/media/com_expautospro/images/big/1843_0.jpg",
      "https://www.autokuatrus.pt/media/com_expautospro/images/big/1843_3.jpg",
      "https://www.autokuatrus.pt/media/com_expautospro/images/big/1843_6.jpg"
    ],
    "sensores": "Yes",
    "seguranca": [
      "ABS",
      "Airbag do passageiro",
      "Controlo de estabilidade (ESP)",
      "Airbag do condutor"
    ],
    "tipofarois": "Xenon & Led"
  }
]
